commandgpt/__init__.py
commandgpt-0.1.1.dist-info/LICENSE
commandgpt-0.1.1.dist-info/METADATA
commandgpt-0.1.1.dist-info/WHEEL
commandgpt-0.1.1.dist-info/entry_points.txt
commandgpt-0.1.1.dist-info/RECORD
