Metadata-Version: 2.1
Name: commandgpt
Version: 0.1.1
Summary: A CLI utility for interacting with OpenAI GPT.
Home-page: https://github.com/michaelknap/commandgpt
License: MIT
Author: Michael Knap
Requires-Python: >=3.6
Classifier: License :: OSI Approved :: MIT License
Classifier: Operating System :: POSIX :: Linux
Classifier: Programming Language :: Python :: 3
Classifier: Programming Language :: Python :: 3.6
Classifier: Programming Language :: Python :: 3.7
Classifier: Programming Language :: Python :: 3.8
Classifier: Programming Language :: Python :: 3.9
Classifier: Programming Language :: Python :: 3.10
Classifier: Programming Language :: Python :: 3.11
Classifier: Programming Language :: Python :: 3.12
Requires-Dist: openai
